inmoose/__init__.py
inmoose/cohort_qc/__init__.py
inmoose/cohort_qc/cohort_metric.py
inmoose/cohort_qc/qc_report.html
inmoose/cohort_qc/qc_report.py
inmoose/consensus_clustering/__init__.py
inmoose/consensus_clustering/consensus_clustering.py
inmoose/data/airway/__init__.py
inmoose/data/airway/airway.h5ad
inmoose/data/pasilla/Dmel.BDGP5.25.62.DEXSeq.chr.gff
inmoose/data/pasilla/__init__.py
inmoose/data/pasilla/geneIDsinsubset.txt
inmoose/data/pasilla/pasilla_gene_counts.tsv
inmoose/data/pasilla/pasilla_sample_annotation.csv
inmoose/data/pasilla/treated1fb.txt
inmoose/data/pasilla/treated2fb.txt
inmoose/data/pasilla/treated3fb.txt
inmoose/data/pasilla/untreated1fb.txt
inmoose/data/pasilla/untreated2fb.txt
inmoose/data/pasilla/untreated3fb.txt
inmoose/data/pasilla/untreated4fb.txt
inmoose/deseq2/DESeqDataSet.py
inmoose/deseq2/DESeqTransform.py
inmoose/deseq2/Hmisc.py
inmoose/deseq2/__init__.py
inmoose/deseq2/core.py
inmoose/deseq2/deseq2_cpp.py
inmoose/deseq2/dispersions.py
inmoose/deseq2/estimateSizeFactors.py
inmoose/deseq2/fitNbinomGLMs.py
inmoose/deseq2/lrt.py
inmoose/deseq2/misc.py
inmoose/deseq2/outliers.py
inmoose/deseq2/parallel.py
inmoose/deseq2/plot.py
inmoose/deseq2/prior.py
inmoose/deseq2/replicates.py
inmoose/deseq2/results.py
inmoose/deseq2/vst.py
inmoose/deseq2/wald.py
inmoose/deseq2/weights.py
inmoose/diffexp/DEResults.py
inmoose/diffexp/__init__.py
inmoose/diffexp/meta.py
inmoose/diffexp/plot.py
inmoose/edgepy/DGEExact.py
inmoose/edgepy/DGEGLM.py
inmoose/edgepy/DGELRT.py
inmoose/edgepy/DGEList.py
inmoose/edgepy/__init__.py
inmoose/edgepy/addPriorCount.py
inmoose/edgepy/adjustedProfileLik.py
inmoose/edgepy/aveLogCPM.py
inmoose/edgepy/binomTest.py
inmoose/edgepy/dispCoxReid.py
inmoose/edgepy/dispCoxReidInterpolateTagwise.py
inmoose/edgepy/edgepy_cpp.cpython-39-darwin.so
inmoose/edgepy/estimateGLMCommonDisp.py
inmoose/edgepy/estimateGLMTagwiseDisp.py
inmoose/edgepy/exactTest.py
inmoose/edgepy/exactTestBetaApprox.py
inmoose/edgepy/exactTestByDeviance.py
inmoosepeapod-0.8.2.dev0.dist-info/licenses/AUTHORS
inmoosepeapod-0.8.2.dev0.dist-info/licenses/LICENSE
inmoosepeapod-0.8.2.dev0.dist-info/METADATA
inmoosepeapod-0.8.2.dev0.dist-info/WHEEL
inmoosepeapod-0.8.2.dev0.dist-info/top_level.txt
inmoosepeapod-0.8.2.dev0.dist-info/RECORD
