Metadata-Version: 2.4
Name: inmoosepeapod
Version: 0.8.2.dev0
Summary: InMoose: the Integrated Multi Omic Open Source Environment, modified for use with PEAPOD
Author-email: Guillaume Appé <guillaume@epigenelabs.com>, Maximilien Colange <maximilien@epigenelabs.com>, Lukaš Gazdik <lukas@epigenelabs.com>, Antoine Gaston <antoine@epigenelabs.com>, Léa Meunier <lea@epigenelabs.com>, Todd Tavernier <todd.tavernier@epigenelabs.com>, Solène Weill <solene@epigenelabs.com>
License-Expression: GPL-3.0-or-later
Project-URL: Source, https://github.com/epigenelabs/inmoose
Project-URL: Documentation, https://inmoose.readthedocs.io/en/latest/
Classifier: Programming Language :: Python :: 3
Classifier: Topic :: Scientific/Engineering :: Bio-Informatics
Requires-Python: >=3.9
License-File: LICENSE
License-File: AUTHORS
Requires-Dist: anndata
Requires-Dist: fastcluster
Requires-Dist: mpmath>=1.1.0
Requires-Dist: numpy
Requires-Dist: pandas
Requires-Dist: patsy
Requires-Dist: scipy<1.16,>=1.11.0
Requires-Dist: seaborn
Requires-Dist: scikit-learn
Requires-Dist: statsmodels>=0.14.3
Requires-Dist: matplotlib
Requires-Dist: jinja2
Provides-Extra: doc
Requires-Dist: scanpy; extra == "doc"
Requires-Dist: sphinx; extra == "doc"
Requires-Dist: sphinx_rtd_theme; extra == "doc"
Requires-Dist: sphinxcontrib-repl; extra == "doc"
Dynamic: license-file
